{"Motorcycle":{"A.P.C. Motor Company":852,"ACM":853,"ATK":854,"All American Choppers":855,"Alpha Sports":856,"American Eagle":857,"American Ironhorse":858,"American Quantum Cycles":859,"American":860,"Apollo Chopper":861,"Aprilia":862,"Arctic Cat":863,"Ariel":864,"Arlen Ness":865,"Aspt":866,"BMC":867,"BMS":868,"BMW":869,"BSA":870,"Baja Motorsports":871,"Bajaj":872,"Benelli":873,"Beta":874,"Big Bear Choppers":875,"Big Dog Motorcycles":876,"Big Inch Bikes":877,"Bimota":878,"Blata":879,"Boss Hoss":880,"Bourget":881,"Brammo ":882,"Buell":883,"CLEVELAND CYCLEWERKS":884,"California Motorcycle Co":885,"California Scooter Co.":886,"California Side Car":887,"Campagna":888,"Can-Am":889,"Carefree Custom Cycles":890,"Cfmoto":891,"Champion Sidecar":892,"Champion Trike Conversion":893,"Christini":894,"Cobra":895,"Condor":896,"Confederate Motorcycles":897,"Coolster":898,"Covington Cycle City":899,"Create A Custom Cycle":900,"Cushman":901,"Custom":902,"DFT":903,"Daelim":904,"Diablo":905,"Diamo":906,"Ducati":907,"E-Ton":908,"EBR":909,"Ecocycle":910,"Eddie Trotta":911,"Enfield":912,"Evolve":913,"Excelsior-Henderson":914,"FN":915,"Gas Gas":916,"Gem":917,"Genuine Scooter Company":918,"Hannigan":919,"Hard-Bikes":920,"Hardcore Choppers":921,"Harley-Davidson":922,"Haulmark":923,"Hercules":924,"Hodaka":925,"Honda":926,"Horex":927,"Husaberg":928,"Husqvarna":929,"Hyosung":930,"Ice Bear":931,"Independence":932,"Indian":933,"Intrepid":934,"JCL":935,"Jawa Cz":936,"Jianshe":937,"Jincheng":938,"Jonway":939,"KTM":940,"Kaotic Customs":941,"Karavan":942,"Kawasaki":943,"Keeway":944,"Knievel":945,"Kraft\/Tech":946,"Kymco":947,"Lambretta":948,"Lance":949,"Lehman Trikes\/Honda":950,"Lehman Trike":951,"Linhai":952,"Lucky 7 Choppers":953,"MOTUS":954,"MZ":955,"Madami":956,"Maico":957,"Malaguti":958,"Marusho":959,"Mid-West Choppers":960,"Montesa":961,"Moto Guzzi":962,"Motobravo":963,"Motofino":964,"Motor Trike Conversion":965,"Motor Trike":966,"Mustang":967,"Mv Agusta":968,"NSU":969,"Norton":970,"Orange County Choppers":971,"Oset":972,"Ossa":973,"Other":975,"Paul Yaffe":976,"Peace Sports":977,"Peirspeed":978,"Penton":979,"Piaggio":980,"Pitster Pro":981,"Pocket Bike":982,"Polaris":983,"Polini":984,"Precision Cycle Works":985,"Pro Street":986,"Pro-One":987,"Proper Chopper":988,"Puch":989,"Qlink":990,"Red Horse":991,"Redcat":992,"Redneck Engineering":993,"Redstreak Motors":994,"Ridley":995,"Road Smith":996,"Roketa":997,"Royal Enfield":998,"Royal Ryder":999,"Rupp":1000,"S&s Manufacturing":1001,"SDG":1002,"SYM":1003,"Sachs":1004,"Santee":1005,"Saxon":1006,"Schwinn Scooters":1007,"Sea Doo":1008,"Segway":1009,"Shenke Motor":1010,"Sherco":1011,"Shoreland'R":1012,"Sikk Mx":1013,"Ski-Doo":1014,"Spcns":1015,"Spencer Bowman":1016,"Ssr Motorsports":1017,"Star Motorcycles":1018,"Streamline":1019,"Suckerpunch Sallys":1020,"Sunbeam":1021,"Surgical-Steeds":1022,"Suzuki":1023,"Swift":1024,"TGB":1025,"Taizhou Zhongneng":1026,"Taotao":1027,"The Trike Shop":1028,"Thoroughbred Motorsports":1029,"Thunder Cycle Designs":1030,"Thunder Mountain Custom":1031,"Titan Motorcycle Co.":1032,"Tomberlin":1033,"Tomos":1034,"Triumph":1035,"Ultima":1036,"Ultra Cycle":1037,"United Motors":1038,"Universal":1039,"Ural":1040,"Vectrix":1041,"Velocette":1042,"Vengeance":1043,"Vento":1044,"Vespa":1045,"Victoria":1046,"Victory":1047,"Viper":1048,"Von Dutch Kustom":1049,"Voyager":1050,"War Eagle Customs":1051,"West Coast Chopper":1052,"Wild West":1053,"Wildfire":1054,"Xingyue":1055,"Xtreme":1056,"Yamaha":1057,"Zero Motorcycles":1058,"Zhejiang Xingyue":1059,"Zhng":1060,"Zieman":1061,"Znen":1062},"ATV":{"ACM":1063,"Alpha Sports":1064,"American Sportworks":1065,"Arctic Cat":1066,"Argo":1067,"BMS":1068,"Bad Boy":1069,"Baja Motorsports":1070,"Bennche":1071,"Bobcat":1072,"Buggy World":1073,"CZ":1074,"Can-Am":1075,"Cannondale":1076,"Cfmoto":1077,"Chenowth":1078,"Club Car":1079,"Coolster":1080,"Cub Cadet":1081,"Custom":1082,"DRR":1083,"Desert Dynamics":1084,"Diamo":1085,"Drakart":1086,"E-Ton":1087,"E-Z-Go":1088,"Echo Trailers":1089,"Gem":1090,"Gibbs":1091,"Hammerhead":1092,"Harley-Davidson":1093,"Haulmark":1094,"High Jumper":1095,"Honda":1096,"Huntve":1097,"Husqvarna":1098,"Hyosung":1099,"Ice Bear":1100,"Jincheng":1101,"John Deere":1102,"Joyner":1103,"KTM":1104,"Karavan":1105,"Kawasaki":1106,"Kubota":1107,"Kymco":1108,"Manx":1109,"Massimo":1110,"Max":1111,"Odes":1112,"Oreion":1113,"Other":1114,"Pitster Pro":1115,"Playtech":1116,"Polar Sport":1117,"Polaris":1118,"Predator Sand Cars":1119,"Qlink":1120,"Raw Motorsports":1121,"Redcat":1122,"Revolution Cycle Company":1123,"Roketa":1124,"Sand Buggy":1125,"Sea Doo":1126,"Superior":1127,"Suzuki":1128,"TGB":1129,"Taotao":1130,"Tatum":1131,"Tj Power Sports":1132,"Tomberlin":1133,"Triumph":1134,"Volkswagen":1135,"Yamaha":1136,"Zieman":1137},"PWC":{"Arctic Cat":1138,"Crownline":1139,"Custom":1140,"Gibbs":1141,"Honda":1142,"Kawasaki":1143,"Mastercraft":1144,"Other":1145,"Polaris":1146,"Sea Doo":1147,"Skeeter":1148,"Suzuki":1149,"Ultra Cycle":1150,"Yamaha":1151},"Snowmobile":{"Arctic Cat":1152,"Harley-Davidson":1153,"Other":1154,"Polaris":1155,"Ski-Doo":1156,"Triton":1157,"Yamaha":1158}}